capture/Dockerfile
capture/VERSION
capture/__init__.py
capture/cli.py
capture/config.py
capture/legacy.py
capture/segmentdata.py
capture/segmentparser.py
capture/sokobon.py
capture/streamer.py
capture/vidtools.py
cuwb_stream/Dockerfile
cuwb_stream/VERSION
cuwb_stream/__init__.py
cuwb_stream/collector.py
cuwb_stream/network.py
cuwb_stream/requirements.txt
cuwb_stream/tools/__init__.py
cuwb_stream/tools/__main__.py
cuwb_stream/tools/snooplogg.py
wf_camera_capture-1.0.3.dist-info/entry_points.txt
wf_camera_capture-1.0.3.dist-info/WHEEL
wf_camera_capture-1.0.3.dist-info/METADATA
wf_camera_capture-1.0.3.dist-info/RECORD
