Metadata-Version: 2.1
Name: wf-camera-capture
Version: 1.0.3
Summary: Capture code for rapspi cameras
License: MIT
Author: Paul J DeCoursey
Author-email: paul@decoursey.net
Requires-Python: >=3.9,<4.0
Classifier: License :: OSI Approved :: MIT License
Classifier: Programming Language :: Python :: 3
Classifier: Programming Language :: Python :: 3.9
Classifier: Programming Language :: Python :: 3.10
Requires-Dist: PyYAML (>=6.0,<7.0)
Requires-Dist: cachetools (>=5.2.0,<6.0.0)
Requires-Dist: click (>=8.1.3,<9.0.0)
Requires-Dist: ffmpeg-python (>=0.2.0,<0.3.0)
Requires-Dist: jmespath (>=1.0.1,<2.0.0)
Requires-Dist: minio (>=7.1.12,<8.0.0)
Requires-Dist: pendulum (>=2.1.2,<3.0.0)
Requires-Dist: watchdog (>=2.1.9,<3.0.0)
